hci_framework/__init__.py
hci_framework/hci_framework/manage.py
hci_framework/hci_framework/hci_framework/__init__.py
hci_framework/hci_framework/hci_framework/asgi.py
hci_framework/hci_framework/hci_framework/settings.py
hci_framework/hci_framework/hci_framework/urls.py
hci_framework/hci_framework/hci_framework/wsgi.py
hci_framework/radiant/__init__.py
hci_framework/radiant/server.py
hci_framework/radiant/template.html
hci_framework/radiant/utils.py
hci_framework/radiant/brython/hci_framework/__init__.py
hci_framework/radiant/brython/hci_framework/radiant/__init__.py
hci_framework/radiant/brython/hci_framework/radiant/figurestream.py
hci_framework/radiant/brython/hci_framework/radiant/server.py
hci_framework/radiant/brython/hci_framework/radiant/utils.py
hci_framework/radiant/python_tools/python_logger.py
hci_framework/radiant/python_tools/python_swarm.py
hci_framework/utils/__init__.py
hci_framework/utils/kafkalogs.py
hci_framework/utils/swarm.py
hci_framework/utils/workers.py
hci_framework/workers/__init__.py
hci_framework/workers/django_worker/db.sqlite3
hci_framework/workers/django_worker/manage.py
hci_framework/workers/django_worker/djangoship/access.log
hci_framework/workers/django_worker/djangoship/error.log
hci_framework/workers/django_worker/djangotest/__init__.py
hci_framework/workers/django_worker/djangotest/asgi.py
hci_framework/workers/django_worker/djangotest/settings.py
hci_framework/workers/django_worker/djangotest/urls.py
hci_framework/workers/django_worker/djangotest/wsgi.py
hci_framework/workers/figurestream_brython_worker/main.py
hci_framework/workers/figurestream_brython_worker/requirements.txt
hci_framework/workers/figurestream_brython_worker/stream.py
hci_framework/workers/figurestream_worker/main.py
hci_framework/workers/figurestream_worker/requirements.txt
hci_framework/workers/main_app/main.py
hci_framework/workers/main_app/requirements.txt
hci_framework/workers/main_app/styles/styles.css
hci_framework-0.1a8.dist-info/LICENSE
hci_framework-0.1a8.dist-info/METADATA
hci_framework-0.1a8.dist-info/WHEEL
hci_framework-0.1a8.dist-info/top_level.txt
hci_framework-0.1a8.dist-info/RECORD
